mzo/__init__.py
mzo/__main__.py
mzo/__version__.py
mzo/accounts.py
mzo/arguments.py
mzo/balance.py
mzo/login.py
mzo/logout.py
mzo/options.py
mzo/pots.py
mzo/transactions.py
mzo/types.py
mzo/utils/__init__.py
mzo/utils/ascii_table.py
mzo/utils/authentication.py
mzo/utils/crypto.py
mzo/utils/csv.py
mzo/utils/dict_helpers.py
mzo/utils/emoji.py
mzo/utils/formats.py
mzo/utils/oauth_server.py
mzo-0.3.2.dist-info/LICENSE
mzo-0.3.2.dist-info/METADATA
mzo-0.3.2.dist-info/WHEEL
mzo-0.3.2.dist-info/entry_points.txt
mzo-0.3.2.dist-info/top_level.txt
mzo-0.3.2.dist-info/RECORD
