Metadata-Version: 2.1
Name: mzo
Version: 0.3.2
Summary: A simple command line interface to your monzo account.
Home-page: https://github.com/jamesstidard/mzo-cli
Author: James Stidard
Author-email: james@stidard.com
License: MIT
Platform: UNKNOWN
Classifier: License :: OSI Approved :: MIT License
Classifier: Programming Language :: Python
Classifier: Programming Language :: Python :: 3
Classifier: Programming Language :: Python :: 3.6
Classifier: Programming Language :: Python :: Implementation :: CPython
Classifier: Programming Language :: Python :: Implementation :: PyPy
Requires-Python: >=3.6.0
Requires-Dist: click
Requires-Dist: aiohttp
Requires-Dist: aioconsole
Requires-Dist: sanic
Requires-Dist: toml
Requires-Dist: pynacl
Requires-Dist: terminaltables
Requires-Dist: ordered-set
Requires-Dist: python-dateutil
Requires-Dist: fuzzywuzzy[speedup]
Requires-Dist: idna (<2.9)
